pandablocks_ioc/__init__.py
pandablocks_ioc/__main__.py
pandablocks_ioc/_connection_status.py
pandablocks_ioc/_hdf_ioc.py
pandablocks_ioc/_pvi.py
pandablocks_ioc/_tables.py
pandablocks_ioc/_types.py
pandablocks_ioc/_version.py
pandablocks_ioc/ioc.py
pandablocks_ioc-0.11.5.dist-info/LICENSE
pandablocks_ioc-0.11.5.dist-info/METADATA
pandablocks_ioc-0.11.5.dist-info/WHEEL
pandablocks_ioc-0.11.5.dist-info/entry_points.txt
pandablocks_ioc-0.11.5.dist-info/top_level.txt
pandablocks_ioc-0.11.5.dist-info/RECORD
