Metadata-Version: 2.1
Name: pandablocks-ioc
Version: 0.11.5
Summary: Create an IOC from a PandA
Author-email: Tom Cobb <tom.cobb@diamond.ac.uk>, Alex Wells <alex.wells@diamond.ac.uk>
License: Apache License
Project-URL: GitHub, https://github.com/PandABlocks/PandABlocks-ioc
Classifier: Development Status :: 3 - Alpha
Classifier: License :: OSI Approved :: Apache Software License
Classifier: Programming Language :: Python :: 3.10
Classifier: Programming Language :: Python :: 3.11
Classifier: Programming Language :: Python :: 3.12
Requires-Python: >=3.10
License-File: LICENSE
Requires-Dist: setuptools >=64
Requires-Dist: numpy <2
Requires-Dist: click
Requires-Dist: h5py
Requires-Dist: softioc >=4.4.0
Requires-Dist: pandablocks ~=0.10.0
Requires-Dist: pvi ~=0.10.0
Requires-Dist: typing-extensions ; python_version < "3.8"
Provides-Extra: dev
Requires-Dist: aioca ; extra == 'dev'
Requires-Dist: black ; extra == 'dev'
Requires-Dist: mock ; extra == 'dev'
Requires-Dist: mypy ; extra == 'dev'
Requires-Dist: copier ; extra == 'dev'
Requires-Dist: myst-parser ; extra == 'dev'
Requires-Dist: pipdeptree ; extra == 'dev'
Requires-Dist: pre-commit ; extra == 'dev'
Requires-Dist: p4p ; extra == 'dev'
Requires-Dist: pydata-sphinx-theme >=0.12 ; extra == 'dev'
Requires-Dist: pytest >=8.2.0 ; extra == 'dev'
Requires-Dist: pytest-asyncio ~=0.21.2 ; extra == 'dev'
Requires-Dist: pytest-cov ; extra == 'dev'
Requires-Dist: ruff ; extra == 'dev'
Requires-Dist: sphinx-autobuild ; extra == 'dev'
Requires-Dist: sphinx-copybutton ; extra == 'dev'
Requires-Dist: sphinx-design ; extra == 'dev'
Requires-Dist: tox-direct ; extra == 'dev'
Requires-Dist: types-mock ; extra == 'dev'
